collective.droproles-1.0.0-py2.7-nspkg.pth
collective/droproles/__init__.py
collective/droproles/patches.py
collective/droproles/testing.py
collective/droproles/utils.py
collective/droproles/tests/__init__.py
collective/droproles/tests/test_functional.py
collective/droproles/tests/test_utils.py
collective.droproles-1.0.0.dist-info/LICENSE.GPL
collective.droproles-1.0.0.dist-info/LICENSE.rst
collective.droproles-1.0.0.dist-info/METADATA
collective.droproles-1.0.0.dist-info/WHEEL
collective.droproles-1.0.0.dist-info/entry_points.txt
collective.droproles-1.0.0.dist-info/namespace_packages.txt
collective.droproles-1.0.0.dist-info/top_level.txt
collective.droproles-1.0.0.dist-info/RECORD
